CHANGELOG.txt
LICENCE.txt
MANIFEST.in
README.txt
setup.py
abrilskopsorting/__init__.py
abrilskopsorting.egg-info/PKG-INFO
abrilskopsorting.egg-info/SOURCES.txt
abrilskopsorting.egg-info/dependency_links.txt
abrilskopsorting.egg-info/top_level.txt