Metadata-Version: 2.1
Name: abrilskopsorting
Version: 0.0.1
Summary: Metodos de Ordenamiento complejos
Home-page: 
Author: Abrilskop
Author-email: uberpot.ia@gmail.com
License: MIT
Keywords: sorting_algorithm
Classifier: Development Status :: 5 - Production/Stable
Classifier: Intended Audience :: Education
Classifier: Operating System :: Microsoft :: Windows :: Windows 10
Classifier: License :: OSI Approved :: MIT License
Classifier: Programming Language :: Python :: 3
License-File: LICENCE.txt
